audp/__init__.py
audp/modems/__init__.py
audp/modems/dac.py
audp/modems/pcm.py
audp-0.9.dist-info/METADATA
audp-0.9.dist-info/WHEEL
audp-0.9.dist-info/licenses/LICENSE
audp-0.9.dist-info/RECORD
