Metadata-Version: 2.3
Name: audp
Version: 0.9
Summary: Analog Unicast Data Protocol (AUDP)
Project-URL: Homepage, https://github.com/logandhillon/audp
Project-URL: Issues, https://github.com/logandhillon/audp/issues
Author-email: Logan Dhillon <logandhi64@gmail.com>
License-File: LICENSE
Classifier: License :: OSI Approved :: GNU General Public License v3 (GPLv3)
Classifier: Operating System :: OS Independent
Classifier: Programming Language :: Python :: 3
Requires-Python: >=3.8
Requires-Dist: numpy==2.0.0
Requires-Dist: scipy==1.14.0
